pricepy/__init__.py
pricepy/pricepy.py
pricepy-0.2.1.dist-info/licenses/LICENSE
pricepy-0.2.1.dist-info/METADATA
pricepy-0.2.1.dist-info/WHEEL
pricepy-0.2.1.dist-info/top_level.txt
pricepy-0.2.1.dist-info/RECORD
