Metadata-Version: 2.4
Name: pricepy
Version: 0.2.1
Summary: Easy-to-use Python library for analyzing price data.
Author: Omer Amin
License-Expression: MIT
Project-URL: Homepage, https://github.com/Omer-Amin/pricepy
Project-URL: Issues, https://github.com/Omer-Amin/pricepy/issues
Classifier: Programming Language :: Python :: 3
Classifier: Operating System :: OS Independent
Requires-Python: >=3.9
License-File: LICENSE
Dynamic: license-file
